redisgraph/__init__.py
redisgraph/edge.py
redisgraph/exceptions.py
redisgraph/execution_plan.py
redisgraph/graph.py
redisgraph/node.py
redisgraph/path.py
redisgraph/query_result.py
redisgraph/util.py
redisgraph-2.4.3.dist-info/LICENSE
redisgraph-2.4.3.dist-info/WHEEL
redisgraph-2.4.3.dist-info/METADATA
redisgraph-2.4.3.dist-info/RECORD
