Metadata-Version: 2.1
Name: redisgraph
Version: 2.4.3
Summary: RedisGraph Python Client
License: BSD-3-Clause
Keywords: Redis,Graph
Author: Redis
Author-email: oss@redis.com
Requires-Python: >=3.6,<4.0
Classifier: Development Status :: 5 - Production/Stable
Classifier: Intended Audience :: Developers
Classifier: License :: OSI Approved :: BSD License
Classifier: Programming Language :: Python
Classifier: Programming Language :: Python :: 3
Classifier: Programming Language :: Python :: 3.10
Classifier: Programming Language :: Python :: 3.6
Classifier: Programming Language :: Python :: 3.7
Classifier: Programming Language :: Python :: 3.8
Classifier: Programming Language :: Python :: 3.9
Classifier: Topic :: Database
Requires-Dist: hiredis (>=2.0.0,<3.0.0)
Requires-Dist: prettytable (>=2.1.0,<3.0.0)
Requires-Dist: redis (==3.5.3)
Project-URL: repository, https://github.com/RedisGraph/redisgraph-py
Project-URL: url, https://redisgraph.io
